itk_rleimage-1.0.2.dist-info/WHEEL
itk_rleimage-1.0.2.dist-info/entry_points.txt
itk_rleimage-1.0.2.dist-info/METADATA
itk_rleimage-1.0.2.dist-info/RECORD
itk_rleimage-1.0.2.dist-info/licenses/LICENSE
itk/RLEImagePython.py
itk/itkRLERegionOfInterestImageFilterPython.py
itk/_RLEImagePython.so
itk/itkRLEImagePython.py
itk/Configuration/RLEImage_snake_case.py
itk/Configuration/RLEImageConfig.py
itk_rleimage.libs/libtbb-3c88584c.so.12.9
